aliyun/bootstrap/__init__.py
aliyun/bootstrap/acm.py
aliyun/bootstrap/bootstrap_gen.py
aliyun/bootstrap/envs.py
aliyun/bootstrap/py.typed
aliyun/bootstrap/utils.py
aliyun/bootstrap/version.py
aliyun_bootstrap-1.0.4.dist-info/METADATA
aliyun_bootstrap-1.0.4.dist-info/WHEEL
aliyun_bootstrap-1.0.4.dist-info/entry_points.txt
aliyun_bootstrap-1.0.4.dist-info/RECORD
